<treebank version="2" xml:lang="grc">
  <sentence struct_id="406" id="1" document_id="0009-002" analysis="manual">
    <word id="100004136" form="παῖδες" line="6.269.1" div_book="6" div_chapter="6.269" lemma="παῖς" postag="n-p---mv-" head="100004141" relation="ExD"/>
    <word id="100004137" form="," line="6.269.1" div_book="6" div_chapter="6.269" lemma="," postag="u--------" head="0" relation="AuxX"/>
    <word id="100004138" form="ἄφωνος" line="6.269.1" div_book="6" div_chapter="6.269" lemma="ἄφωνος" postag="a-s---fn-" head="100004139" relation="PNOM"/>
    <word id="100004139" form="ἐοῖσα" line="6.269.1" div_book="6" div_chapter="6.269" lemma="εἰμί" postag="v-sppafn-" head="100004141" relation="ADV"/>
    <word id="100004140" form="τορ’" line="6.269.1" div_book="6" div_chapter="6.269" lemma="πρός" postag="d--------" head="100004141" relation="AuxZ"/>
    <word id="100004141" form="ἐννέπω" line="6.269.1" div_book="6" div_chapter="6.269" lemma="ἐνέπω" postag="v1spia---" head="0" relation="PRED"/>
    <word id="100004142" form="," line="6.269.1" div_book="6" div_chapter="6.269" lemma="," postag="u--------" head="0" relation="AuxX"/>
    <word id="100004143" form="αἴ" line="6.269.1" div_book="6" div_chapter="6.269" lemma="εἰ" postag="c--------" head="100004141" relation="AuxC"/>
    <word id="100004144" form="τις" line="6.269.1" div_book="6" div_chapter="6.269" lemma="τις" postag="p-s---cn-" head="100004145" relation="SBJ"/>
    <word id="100004145" form="ἔρηται" line="6.269.1" div_book="6" div_chapter="6.269" lemma="ἐράω" postag="v3spim---" head="100004143" relation="ADV"/>
    <word id="100004146" form="," line="6.269.1" div_book="6" div_chapter="6.269" lemma="," postag="u--------" head="0" relation="AuxX"/>
    <word id="100004147" form="φωνὰν" line="6.269.2" div_book="6" div_chapter="6.269" lemma="φωνή" postag="n-s---fa-" head="100004149" relation="OBJ"/>
    <word id="100004148" form="ἀκαμάταν" line="6.269.2" div_book="6" div_chapter="6.269" lemma="ἀκάματος" postag="a-s---fa-" head="100004147" relation="ATR"/>
    <word id="100004149" form="κατθεμένα" line="6.269.2" div_book="6" div_chapter="6.269" lemma="κατατίθημι" postag="v-sapmfn-" head="100004141" relation="ADV"/>
    <word id="100004150" form="πρὸ" line="6.269.2" div_book="6" div_chapter="6.269" lemma="πρό" postag="r--------" head="100004149" relation="AuxP"/>
    <word id="100004151" form="ποδῶν" line="6.269.2" div_book="6" div_chapter="6.269" lemma="πούς" postag="n-p---mg-" head="100004150" relation="ADV"/>
    <word id="100004152" form="·" line="6.269.2" div_book="6" div_chapter="6.269" lemma="·" postag="u--------" head="0" relation="AuxK"/>
  </sentence>
  <sentence struct_id="407" id="2" document_id="0009-002" analysis="manual">
    <word id="100004153" form="&quot;" line="6.269.3" div_book="6" div_chapter="6.269" lemma="&quot;" postag="u--------" head="0" relation="AuxG"/>
    <word id="100004154" form="Αἰθοπίᾳ" line="6.269.3" div_book="6" div_chapter="6.269" lemma="Αἰθιοπία" postag="n-s---fd-" head="100004158" relation="OBJ"/>
    <word id="100004155" form="με" line="6.269.3" div_book="6" div_chapter="6.269" lemma="ἐγώ" postag="p1s---ca-" head="100004158" relation="OBJ"/>
    <word id="100004156" form="κόρᾳ" line="6.269.3" div_book="6" div_chapter="6.269" lemma="κόρη" postag="n-s---fd-" head="100004154" relation="APOS"/>
    <word id="100004157" form="Λατοῦς" line="6.269.3" div_book="6" div_chapter="6.269" lemma="Λητώ" postag="n-s---fg-" head="100004156" relation="ATR"/>
    <word id="100004158" form="ἀνέθηκεν" line="6.269.3" div_book="6" div_chapter="6.269" lemma="ἀνατίθημι" postag="v3saia---" head="0" relation="PRED"/>
    <word id="100004159" form="Ἀρίστα" line="6.269.3" div_book="6" div_chapter="6.269" lemma="Ἀρίστη" postag="n-s---fn-" head="100004158" relation="SBJ"/>
    <word id="100004160" form="ἁ" line="6.269.4" div_book="6" div_chapter="6.269" lemma="ὁ" postag="l-s---fn-" head="100004159" relation="ATR"/>
    <word id="100004161" form="Ἑρμοκλείδα" line="6.269.4" div_book="6" div_chapter="6.269" lemma="Ἑρμοκλείδης" postag="n-s---mg-" head="100004159" relation="ATR"/>
    <word id="100004162" form="τῶ" line="6.269.4" div_book="6" div_chapter="6.269" lemma="ὁ" postag="l-s---mg-" head="100004161" relation="ATR"/>
    <word id="100004163" form="Σαϋναϊάδα" line="6.269.4" div_book="6" div_chapter="6.269" lemma="Σαϋναϊάδας" postag="n-s---mg-" head="100004161" relation="ATR"/>
    <word id="100004164" form="," line="6.269.4" div_book="6" div_chapter="6.269" lemma="," postag="u--------" head="0" relation="AuxX"/>
    <word id="100004165" form="σὰ" line="6.269.5" div_book="6" div_chapter="6.269" lemma="σός" postag="a-s---fn-" head="100004166" relation="ATR"/>
    <word id="100004166" form="πρόπολος" line="6.269.5" div_book="6" div_chapter="6.269" lemma="πρόπολος" postag="a-s---fn-" head="100004159" relation="APOS"/>
    <word id="100004167" form="," line="6.269.5" div_book="6" div_chapter="6.269" lemma="," postag="u--------" head="0" relation="AuxX"/>
    <word id="100004168" form="δέσποινα" line="6.269.5" div_book="6" div_chapter="6.269" lemma="δέσποινα" postag="n-s---fn-" head="100004159" relation="APOS"/>
    <word id="100004169" form="γυναικῶν" line="6.269.5" div_book="6" div_chapter="6.269" lemma="γυνή" postag="n-p---fg-" head="100004168" relation="ATR"/>
    <word id="100004170" form="·" line="6.269.5" div_book="6" div_chapter="6.269" lemma="·" postag="u--------" head="0" relation="AuxK"/>
  </sentence>
  <sentence struct_id="408" id="3" document_id="0009-002" analysis="manual">
    <word id="100004171" form="ᾇ" line="6.269.5" div_book="6" div_chapter="6.269" lemma="ὅς" postag="p-s---fd-" head="100004173" relation="OBJ"/>
    <word id="100004172" form="σὺ" line="6.269.5" div_book="6" div_chapter="6.269" lemma="σύ" postag="p2s---cn-" head="100004176" relation="SBJ"/>
    <word id="100004173" form="χαρεῖσα" line="6.269.5" div_book="6" div_chapter="6.269" lemma="χαίρω" postag="v-sappfn-" head="100004176" relation="ADV"/>
    <word id="100004174" form="πρόφρων" line="6.269.6" div_book="6" div_chapter="6.269" lemma="πρόφρων" postag="a-s---fn-" head="100004176" relation="ADV"/>
    <word id="100004175" form="ἁμετέραν" line="6.269.6" div_book="6" div_chapter="6.269" lemma="ἡμέτερος" postag="a-s---fa-" head="100004177" relation="ATR"/>
    <word id="100004176" form="εὐκλέισον" line="6.269.6" div_book="6" div_chapter="6.269" lemma="εὐκλείζω" postag="v2sama---" head="0" relation="PRED"/>
    <word id="100004177" form="γενεάν" line="6.269.6" div_book="6" div_chapter="6.269" lemma="γενεά" postag="n-s---fa-" head="100004176" relation="OBJ"/>
    <word id="100004178" form="&quot;" line="6.269.6" div_book="6" div_chapter="6.269" lemma="&quot;" postag="u--------" head="0" relation="AuxG"/>
    <word id="100004179" form="." line="6.269.6" div_book="6" div_chapter="6.269" lemma="." postag="u--------" head="0" relation="AuxK"/>
  </sentence>
  <sentence struct_id="409" id="4" document_id="0009-002" analysis="manual">
    <word id="100004180" form="Τιμάδος" line="7.489.1" div_book="7" div_chapter="7.489" lemma="Τιμάς" postag="n-s---fg-" head="100004182" relation="ATR"/>
    <word id="100004181" form="ἅδε" line="7.489.1" div_book="7" div_chapter="7.489" lemma="ὅδε" postag="p-s---fn-" head="1000001868" relation="SBJ"/>
    <word id="100004182" form="κόνις" line="7.489.1" div_book="7" div_chapter="7.489" lemma="κόνις" postag="n-s---fn-" head="1000001868" relation="PNOM"/>
    <word id="100004183" form="," line="7.489.1" div_book="7" div_chapter="7.489" lemma="," postag="u--------" head="0" relation="AuxX"/>
    <word id="100004184" form="τὰν" line="7.489.1" div_book="7" div_chapter="7.489" lemma="ὁ" postag="l-s---fa-" head="100004189" relation="OBJ"/>
    <word id="100004185" form="δὴ" line="7.489.1" div_book="7" div_chapter="7.489" lemma="δή" postag="g--------" head="100004189" relation="AuxY"/>
    <word id="100004186" form="πρὸ" line="7.489.1" div_book="7" div_chapter="7.489" lemma="πρό" postag="r--------" head="100004188" relation="AuxP"/>
    <word id="100004187" form="γάμοιο" line="7.489.1" div_book="7" div_chapter="7.489" lemma="γάμος" postag="n-s---mg-" head="100004186" relation="ADV"/>
    <word id="100004188" form="θανοῦσαν" line="7.489.1" div_book="7" div_chapter="7.489" lemma="θνῄσκω" postag="v-sapafa-" head="100004189" relation="ADV"/>
    <word id="100004189" form="δέξατο" line="7.489.2" div_book="7" div_chapter="7.489" lemma="δέχομαι" postag="v3saim---" head="100004195" relation="PRED_CO"/>
    <word id="100004190" form="Φερσεφόνας" line="7.489.2" div_book="7" div_chapter="7.489" lemma="Περσεφόνη" postag="n-s---fg-" head="100004192" relation="ATR"/>
    <word id="100004191" form="κυάνεος" line="7.489.2" div_book="7" div_chapter="7.489" lemma="κυάνεος" postag="a-s---mn-" head="100004192" relation="ATR"/>
    <word id="100004192" form="θάλαμος" line="7.489.2" div_book="7" div_chapter="7.489" lemma="θάλαμος" postag="n-s---mn-" head="100004189" relation="SBJ"/>
    <word id="100004193" form="," line="7.489.2" div_book="7" div_chapter="7.489" lemma="," postag="u--------" head="0" relation="AuxX"/>
    <word id="100004194" form="ἇς" line="7.489.3" div_book="7" div_chapter="7.489" lemma="ὅς" postag="p-s---fg-" head="100004196" relation="SBJ"/>
    <word id="100004195" form="καὶ" line="7.489.3" div_book="7" div_chapter="7.489" lemma="καί" postag="b--------" head="0" relation="COORD"/>
    <word id="100004196" form="ἀποφθιμένας" line="7.489.3" div_book="7" div_chapter="7.489" lemma="ἀποφθίνω" postag="v-sapmfg-" head="100004203" relation="ADV"/>
    <word id="100004197" form="πᾶσαι" line="7.489.3" div_book="7" div_chapter="7.489" lemma="πᾶς" postag="a-p---fn-" head="100004200" relation="ATR"/>
    <word id="100004198" form="νεοθᾶγι" line="7.489.3" div_book="7" div_chapter="7.489" lemma="νεοθήξ" postag="a-s---md-" head="100004199" relation="ATR"/>
    <word id="100004199" form="σιδάρῳ" line="7.489.3" div_book="7" div_chapter="7.489" lemma="σίδηρος" postag="n-s---md-" head="100004203" relation="ADV"/>
    <word id="100004200" form="ἅλικες" line="7.489.4" div_book="7" div_chapter="7.489" lemma="ἧλιξ" postag="n-p---fn-" head="100004203" relation="SBJ"/>
    <word id="100004201" form="ἱμερτὰν" line="7.489.4" div_book="7" div_chapter="7.489" lemma="ἱμερτός" postag="a-s---fa-" head="100004204" relation="ATR"/>
    <word id="100004202" form="κρατὸς" line="7.489.4" div_book="7" div_chapter="7.489" lemma="κράς" postag="n-s---ng-" head="100004204" relation="ATR"/>
    <word id="100004203" form="ἔθεντο" line="7.489.4" div_book="7" div_chapter="7.489" lemma="τίθημι" postag="v3paim---" head="100004195" relation="PRED_CO"/>
    <word id="100004204" form="κόμαν" line="7.489.4" div_book="7" div_chapter="7.489" lemma="κόμη" postag="n-s---fa-" head="100004203" relation="OBJ"/>
    <word id="100004205" form="." line="7.489.4" div_book="7" div_chapter="7.489" lemma="." postag="u--------" head="0" relation="AuxK"/>
    <word id="1000001868" form="E" lemma="E" postag="z--------" head="100004195" relation="PRED_CO" artificial="elliptic" line="7.489.4" div_book="7" div_chapter="7.489"/>
  </sentence>
  <sentence struct_id="410" id="5" document_id="0009-002" analysis="manual">
    <word id="100004206" form="τῷ" line="7.505.1" div_book="7" div_chapter="7.505" lemma="ὁ" postag="l-s---md-" head="100004207" relation="ATR"/>
    <word id="100004207" form="γριπεῖ" line="7.505.1" div_book="7" div_chapter="7.505" lemma="γριπεύς" postag="n-s---md-" head="100004208" relation="APOS"/>
    <word id="100004208" form="Πελάγωνι" line="7.505.1" div_book="7" div_chapter="7.505" lemma="Πελάγων" postag="n-s---md-" head="100004210" relation="OBJ"/>
    <word id="100004209" form="πατὴρ" line="7.505.1" div_book="7" div_chapter="7.505" lemma="πατήρ" postag="n-s---mn-" head="100004210" relation="SBJ"/>
    <word id="100004210" form="ἐπέθηκε" line="7.505.1" div_book="7" div_chapter="7.505" lemma="ἐπιτίθημι" postag="v3saia---" head="0" relation="PRED"/>
    <word id="100004211" form="Μενίσκος" line="7.505.1" div_book="7" div_chapter="7.505" lemma="Μενίσκος" postag="n-s---mn-" head="100004209" relation="APOS"/>
    <word id="100004212" form="κύρτον" line="7.505.2" div_book="7" div_chapter="7.505" lemma="κύρτος" postag="n-s---ma-" head="100004213" relation="OBJ_CO"/>
    <word id="100004213" form="καὶ" line="7.505.2" div_book="7" div_chapter="7.505" lemma="καί" postag="b--------" head="100004210" relation="COORD"/>
    <word id="100004214" form="κώπαν" line="7.505.2" div_book="7" div_chapter="7.505" lemma="κώπη" postag="n-s---fa-" head="100004213" relation="OBJ_CO"/>
    <word id="100004215" form="," line="7.505.2" div_book="7" div_chapter="7.505" lemma="," postag="u--------" head="0" relation="AuxX"/>
    <word id="100004216" form="μνᾶμα" line="7.505.2" div_book="7" div_chapter="7.505" lemma="μνῆμα" postag="n-s---na-" head="100004213" relation="APOS"/>
    <word id="100004217" form="κακοζοΐας" line="7.505.2" div_book="7" div_chapter="7.505" lemma="κακοζοΐα" postag="n-s---fg-" head="100004216" relation="ATR"/>
    <word id="100004218" form="." line="7.505.2" div_book="7" div_chapter="7.505" lemma="." postag="u--------" head="0" relation="AuxK"/>
  </sentence>
</treebank>